ondil/__init__.py
ondil/coordinate_descent.py
ondil/design_matrix.py
ondil/diagnostics.py
ondil/error.py
ondil/gram.py
ondil/information_criteria.py
ondil/robust_math.py
ondil/scaler.py
ondil/types.py
ondil/utils.py
ondil/validation.py
ondil/warnings.py
ondil/base/__init__.py
ondil/base/display.py
ondil/base/distribution.py
ondil/base/estimation_method.py
ondil/base/estimator.py
ondil/base/link.py
ondil/distributions/__init__.py
ondil/distributions/beta.py
ondil/distributions/betainflated.py
ondil/distributions/betainflatedzero.py
ondil/distributions/exponential.py
ondil/distributions/gamma.py
ondil/distributions/gumbel.py
ondil/distributions/inversegamma.py
ondil/distributions/inversegaussian.py
ondil/distributions/johnsonsu.py
ondil/distributions/logistic.py
ondil/distributions/lognormal.py
ondil/distributions/lognormalmedian.py
ondil/distributions/mv_normal_chol.py
ondil/distributions/mv_normal_low_rank.py
ondil/distributions/mv_normal_modchol.py
ondil/distributions/mv_t_chol.py
ondil/distributions/mv_t_low_rank.py
ondil/distributions/mv_t_modchol.py
ondil/distributions/normal.py
ondil/distributions/poisson.py
ondil/distributions/powerexponential.py
ondil/distributions/reversegumbel.py
ondil/distributions/skew_t.py
ondil/distributions/studentt.py
ondil/distributions/weibull.py
ondil/distributions/zeroadjustedgamma.py
ondil/estimators/__init__.py
ondil/estimators/online_gamlss.py
ondil/estimators/online_lasso.py
ondil/estimators/online_linear_model.py
ondil/estimators/online_mvdistreg.py
ondil/links/__init__.py
ondil/links/identitylinks.py
ondil/links/logitlinks.py
ondil/links/loglinks.py
ondil/links/matrixlinks.py
ondil/links/softpluslinks.py
ondil/links/sqrtlinks.py
ondil/methods/__init__.py
ondil/methods/elasticnet.py
ondil/methods/factory.py
ondil/methods/lasso_path.py
ondil/methods/recursive_least_squares.py
ondil/methods/ridge.py
ondil-0.4.6.dist-info/licenses/LICENSE.md
ondil-0.4.6.dist-info/METADATA
ondil-0.4.6.dist-info/WHEEL
ondil-0.4.6.dist-info/top_level.txt
ondil-0.4.6.dist-info/RECORD
