Metadata-Version: 2.4
Name: ondil
Version: 0.4.6
Summary: Methods for online / incremental estimation of distributional regression models
Author-email: Simon Hirsch <simon.hirsch@stud.uni-due.de>, Jonathan Berrisch <jonathan.berrisch@uni-due.de>, Florian Ziel <florian.ziel@uni-due.de>
License-Expression: GPL-3.0-only
Project-URL: Homepage, https://github.com/simon-hirsch/ondil
Classifier: Programming Language :: Python :: 3
Classifier: Programming Language :: Python :: 3.10
Classifier: Programming Language :: Python :: 3.11
Classifier: Programming Language :: Python :: 3.12
Classifier: Programming Language :: Python :: 3.13
Classifier: Operating System :: OS Independent
Classifier: Topic :: Scientific/Engineering
Classifier: Topic :: Scientific/Engineering :: Mathematics
Classifier: Topic :: Scientific/Engineering :: Information Analysis
Classifier: Intended Audience :: Science/Research
Classifier: Intended Audience :: Developers
Classifier: Intended Audience :: Education
Classifier: Intended Audience :: Financial and Insurance Industry
Classifier: Intended Audience :: Information Technology
Classifier: Intended Audience :: Healthcare Industry
Classifier: Intended Audience :: Manufacturing
Classifier: Intended Audience :: Telecommunications Industry
Classifier: Intended Audience :: Other Audience
Requires-Python: <3.14,>=3.10
License-File: LICENSE.md
Requires-Dist: scipy<2.2.0,>=1.00
Requires-Dist: numpy<=2.1.0,>=1.2
Requires-Dist: numba<1.0.0,>=0.59.1
Requires-Dist: scikit-learn>=1.5
Provides-Extra: pandas
Requires-Dist: pandas>=1.20; extra == "pandas"
Provides-Extra: polars
Requires-Dist: polars; extra == "polars"
Provides-Extra: mpl
Requires-Dist: matplotlib>=3.7; extra == "mpl"
Provides-Extra: all
Requires-Dist: ondil[mpl,pandas,polars]; extra == "all"
Dynamic: license-file
